app/__init__.py
app/cli.py
app/config.py
app/dingtalk_doc_reader.py
app/notifier.py
app/models/__init__.py
app/models/price_result.py
app/notifiers/__init__.py
app/readers/__init__.py
app/readers/sku_reader.py
app/recorders/__init__.py
app/recorders/price_recorder.py
app/selectors/__init__.py
app/selectors/walmart_selectors.py
app/spiders/__init__.py
app/spiders/base_spider.py
app/spiders/walmart_bot_handler.py
app/spiders/walmart_spider.py
walmart_price_monitor-0.2.0.dist-info/METADATA
walmart_price_monitor-0.2.0.dist-info/WHEEL
walmart_price_monitor-0.2.0.dist-info/entry_points.txt
walmart_price_monitor-0.2.0.dist-info/RECORD
