Metadata-Version: 2.4
Name: walmart-price-monitor
Version: 0.2.0
Summary: 沃尔玛价格监控工具 - 每天定时获取商品价格并写入钉钉表格
Project-URL: Homepage, https://github.com/yourusername/walmart-price-monitor
Project-URL: Repository, https://github.com/yourusername/walmart-price-monitor
Author: Leo
License: MIT
Keywords: dingtalk,price-monitor,spider,walmart
Classifier: Development Status :: 4 - Beta
Classifier: Environment :: Console
Classifier: Intended Audience :: Developers
Classifier: License :: OSI Approved :: MIT License
Classifier: Operating System :: OS Independent
Classifier: Programming Language :: Python :: 3
Classifier: Programming Language :: Python :: 3.9
Classifier: Programming Language :: Python :: 3.10
Classifier: Programming Language :: Python :: 3.11
Classifier: Programming Language :: Python :: 3.12
Classifier: Topic :: Internet :: WWW/HTTP :: Indexing/Search
Requires-Python: >=3.9
Requires-Dist: alibabacloud-dingtalk>=2.0.0
Requires-Dist: croniter>=2.0.0
Requires-Dist: dingtalkchatbot>=1.5.0
Requires-Dist: drissionpage>=4.0.0
Requires-Dist: python-dotenv>=1.0.0
Provides-Extra: dev
Requires-Dist: pytest>=7.0.0; extra == 'dev'
Requires-Dist: ruff>=0.1.0; extra == 'dev'
